cogent3_pykmertools/__init__.py
cogent3_pykmertools-0.2.2.dist-info/entry_points.txt
cogent3_pykmertools-0.2.2.dist-info/licenses/LICENSE
cogent3_pykmertools-0.2.2.dist-info/WHEEL
cogent3_pykmertools-0.2.2.dist-info/METADATA
cogent3_pykmertools-0.2.2.dist-info/RECORD
