Metadata-Version: 2.4
Name: cogent3_pykmertools
Version: 0.2.2
Summary: A cogent3 pykmertools app
Author-email: Anuradha Wickramarachchi <anuradhawick@gmail.com>
Requires-Python: >=3.11,<3.14
Classifier: Development Status :: 2 - Pre-Alpha
Classifier: Intended Audience :: Science/Research
Classifier: License :: OSI Approved :: GNU General Public License v3 (GPLv3)
Classifier: Topic :: Scientific/Engineering :: Bio-Informatics
Classifier: Topic :: Software Development :: Libraries :: Python Modules
Classifier: Operating System :: OS Independent
Classifier: Programming Language :: Python :: 3.11
Classifier: Programming Language :: Python :: 3.12
Classifier: Programming Language :: Python :: 3.13
License-File: LICENSE
Requires-Dist: cogent3>=2025.9.8a4
Requires-Dist: pykmertools>=0.2.1
Requires-Dist: ruff ; extra == "dev"
Requires-Dist: cogent3_pykmertools[test] ; extra == "dev"
Requires-Dist: pytest ; extra == "test"
Requires-Dist: pytest-cov ; extra == "test"
Requires-Dist: nox ; extra == "test"
Provides-Extra: dev
Provides-Extra: test
